ts_forecasting_pipeline/__init__.py
ts_forecasting_pipeline/exceptions.py
ts_forecasting_pipeline/featuring.py
ts_forecasting_pipeline/forecasting.py
ts_forecasting_pipeline/modelling.py
ts_forecasting_pipeline/serializing.py
ts_forecasting_pipeline/speccing.py
ts_forecasting_pipeline/utils/__init__.py
ts_forecasting_pipeline/utils/debug_utils.py
ts_forecasting_pipeline/utils/time_utils.py
ts_forecasting_pipeline-0.4.0.dist-info/METADATA
ts_forecasting_pipeline-0.4.0.dist-info/RECORD
ts_forecasting_pipeline-0.4.0.dist-info/WHEEL
ts_forecasting_pipeline-0.4.0.dist-info/top_level.txt
