Metadata-Version: 2.1
Name: ts-forecasting-pipeline
Version: 0.4.0
Summary: Toolset for time series forecasting. Supports both basic modeling and in-production usage.
Home-page: UNKNOWN
Author: Seita BV
Author-email: nicolas@seita.nl
License: UNKNOWN
Keywords: time series,forecasting
Platform: UNKNOWN
Classifier: Programming Language :: Python
Classifier: Programming Language :: Python :: 3
Classifier: Development Status :: 3 - Alpha
Classifier: Intended Audience :: Developers
Classifier: License :: OSI Approved :: Apache Software License
Classifier: Operating System :: OS Independent
Classifier: Topic :: Software Development :: Libraries :: Python Modules
Classifier: Topic :: Scientific/Engineering :: Information Analysis
Requires-Dist: pandas
Requires-Dist: statsmodels
Requires-Dist: sklearn
Requires-Dist: matplotlib
Requires-Dist: numpy
Requires-Dist: scipy
Requires-Dist: pytz
Requires-Dist: python-dateutil (>=2.5)
Requires-Dist: SQLALchemy
